meican/__init__.py
meican/cmdline.py
meican/commands.py
meican/exceptions.py
meican/models.py
meican/settings.py
meican/tools.py
meican-0.4.3.dist-info/LICENSE
meican-0.4.3.dist-info/METADATA
meican-0.4.3.dist-info/WHEEL
meican-0.4.3.dist-info/entry_points.txt
meican-0.4.3.dist-info/top_level.txt
meican-0.4.3.dist-info/RECORD
