Metadata-Version: 2.1
Name: meican
Version: 0.4.3
Summary: UNOFFICIAL meican command line / sdk
Home-page: https://github.com/LKI/meican
Author: Lirian Su
Author-email: liriansu@gmail.com
License: MIT License
Platform: UNKNOWN
Requires-Dist: pytz (>=2019.3)
Requires-Dist: requests (>=2.21.0)
